README
setup.py
everjoke.egg-info/PKG-INFO
everjoke.egg-info/SOURCES.txt
everjoke.egg-info/dependency_links.txt
everjoke.egg-info/entry_points.txt
everjoke.egg-info/requires.txt
everjoke.egg-info/top_level.txt
everjokeCLI/EverjokeCLI.py
everjokeCLI/__init__.py
everjokeCLI/jokes.py
everjokeCLI/test.py