Metadata-Version: 1.0
Name: everjoke
Version: 0.2.2
Summary: Write and Manage Jokes
Home-page: UNKNOWN
Author: Cody Hess
Author-email: cody.hess@gmail.com
License: UNKNOWN
Platform: UNKNOWN
Classifier: Programming Language :: Python
Classifier: Development Status :: 3 - Alpha
Classifier: Environment :: Console
Classifier: Operating System :: MacOS :: MacOS X
